COPYING.txt
MANIFEST.in
README
README.rst
setup.py
pyredmine.egg-info/PKG-INFO
pyredmine.egg-info/SOURCES.txt
pyredmine.egg-info/dependency_links.txt
pyredmine.egg-info/top_level.txt
redmine/__init__.py
redmine/redmine.py
redmine/redmine_rest.py