Metadata-Version: 1.0
Name: pyredmine
Version: 0.2.4
Summary: Python Redmine Web Services Library
Home-page: https://github.com/ianepperson/pyredminews
Author: Ian Epperson
Author-email: ian@epperson.com
License: UNKNOWN
Keywords: redmine,server
Platform: UNKNOWN
Classifier: Programming Language :: Python
Classifier: Development Status :: 3 - Alpha
Classifier: Environment :: Other Environment
Classifier: Intended Audience :: Developers
Classifier: License :: OSI Approved :: GNU General Public License v3 or later (GPLv3+)
Classifier: Operating System :: OS Independent
Classifier: Topic :: Software Development :: Libraries :: Python Modules
Classifier: Topic :: Office/Business :: Groupware
Classifier: Topic :: Utilities
Classifier: Topic :: Internet :: WWW/HTTP :: Site Management
